retractions/__init__.py
retractions/cli.py
retractions/doi.py
retractions/version.py
retractions-0.1.dist-info/LICENSE
retractions-0.1.dist-info/METADATA
retractions-0.1.dist-info/WHEEL
retractions-0.1.dist-info/entry_points.txt
retractions-0.1.dist-info/top_level.txt
retractions-0.1.dist-info/RECORD
