Metadata-Version: 2.1
Name: retractions
Version: 0.1
Summary: Check DOIs for retractions
Home-page: https://github.com/clbarnes/retractions
Author: Chris L. Barnes
License: UNKNOWN
Platform: UNKNOWN
Classifier: Development Status :: 3 - Alpha
Classifier: License :: OSI Approved :: MIT License
Classifier: Programming Language :: Python :: 3
Classifier: Programming Language :: Python :: 3.8
Classifier: Programming Language :: Python :: 3.9
Classifier: Programming Language :: Python :: 3.10
Requires-Python: >=3.8, <4.0
License-File: LICENSE
Provides-Extra: cli
Requires-Dist: httpx ; extra == 'cli'
